zyz/__init__.py
zyz/zlog/__init__.py
zhouyuanzhen-0.5.0.dist-info/METADATA
zhouyuanzhen-0.5.0.dist-info/WHEEL
zhouyuanzhen-0.5.0.dist-info/top_level.txt
zhouyuanzhen-0.5.0.dist-info/RECORD
