Metadata-Version: 2.1
Name: zhouyuanzhen
Version: 0.5.0
Summary: A PyPI project of zhouyuanzhen
Home-page: https://github.com/zhouyuanzhen/py-zhouyuanzhen
Author: Yuanzhen Zhou
Author-email: szrednick@gmail.com
Maintainer: Yuanzhen Zhou
Maintainer-email: szrednick@gmail.com
License: Apache License 2.0
Keywords: zyz,zhouyuanzhen,development
Platform: UNKNOWN
Requires-Python: >=3.5, <4
Provides-Extra: test
Requires-Dist: pytest ; extra == 'test'
Requires-Dist: coverage ; extra == 'test'
